pyfd/__init__.py
pyfd-0.2.0.dist-info/LICENSE
pyfd-0.2.0.dist-info/METADATA
pyfd-0.2.0.dist-info/WHEEL
pyfd-0.2.0.dist-info/top_level.txt
pyfd-0.2.0.dist-info/RECORD
