Metadata-Version: 2.1
Name: pyfd
Version: 0.2.0
Summary: A Python wrapper for the Freshdesk API
Home-page: https://github.com/dish-freshdesk/pyfd
Author: Tim Sessanna
Author-email: timothy.sessanna@dish.com
License: UNKNOWN
Platform: UNKNOWN
Classifier: Programming Language :: Python :: 3
Classifier: License :: OSI Approved :: MIT License
Classifier: Operating System :: OS Independent
